openmeteo_py/Daily.py
openmeteo_py/Hourly.py
openmeteo_py/OWmanager.py
openmeteo_py/Options.py
openmeteo_py/__init__.py
openmeteo_py/constants.py
openmeteo_py/timezones.py
openmeteo_py/utils.py
openmeteo_py-0.0.1.dist-info/LICENSE
openmeteo_py-0.0.1.dist-info/METADATA
openmeteo_py-0.0.1.dist-info/WHEEL
openmeteo_py-0.0.1.dist-info/top_level.txt
openmeteo_py-0.0.1.dist-info/RECORD
