Metadata-Version: 2.1
Name: openmeteo_py
Version: 0.0.1
Summary: Download Meteorological Data from OPEN-METEO API (https://open-meteo.com/en/)
Home-page: https://github.com/m0rp43us/openmeteopy
Author: Wail Chalabi
Author-email: wail.agroconcept@gmail.com
License: GNU General Public License v3 or later (GPLv3+)
Platform: UNKNOWN
Classifier: Programming Language :: Python :: 3
Classifier: License :: OSI Approved :: GNU General Public License v3 or later (GPLv3+)
Classifier: Operating System :: OS Independent
Requires-Python: >=3.6
License-File: LICENSE
